{
    "versionCode":  385,
    "versionName":  "3.4.38-ZBH",
    "publishedAt":  "2026-06-17T16:23:42Z",
    "changelog":  "移动端设置页新增「调试」页面，可在应用内直接查看日志、网络请求、VodConfig 状态；设置页显示调试 URL，支持复制",
    "minSupportedVersionCode":  384,
    "variants":  {
                     "mobile":  {
                                    "v8a":  {
                                                "urls":  [
                                                             "https://gh-proxy.com/https://raw.githubusercontent.com/MrZhaobh/my-releases/main/ZBH_FongTV/dist/mobile-v8a.apk",
                                                             "https://ghfast.top/https://raw.githubusercontent.com/MrZhaobh/my-releases/main/ZBH_FongTV/dist/mobile-v8a.apk",
                                                             "https://raw.githubusercontent.com/MrZhaobh/my-releases/main/ZBH_FongTV/dist/mobile-v8a.apk"
                                                         ],
                                                "github":  "https://gh-proxy.com/https://raw.githubusercontent.com/MrZhaobh/my-releases/main/ZBH_FongTV/dist/mobile-v8a.apk",
                                                "gitee":  "https://ghfast.top/https://raw.githubusercontent.com/MrZhaobh/my-releases/main/ZBH_FongTV/dist/mobile-v8a.apk",
                                                "sha256":  "cd47f0b11374d0a64563638bb9f601156cc27279c8bf5b6003d828607032905e",
                                                "sizeMB":  30.87
                                            }
                                }
                 },
    "mirrors":  {

                }
}